odoo/addons/stock_picking_type_user_restriction/README.rst
odoo/addons/stock_picking_type_user_restriction/__init__.py
odoo/addons/stock_picking_type_user_restriction/__manifest__.py
odoo/addons/stock_picking_type_user_restriction/i18n/it.po
odoo/addons/stock_picking_type_user_restriction/i18n/stock_picking_type_user_restriction.pot
odoo/addons/stock_picking_type_user_restriction/models/__init__.py
odoo/addons/stock_picking_type_user_restriction/models/stock_picking_type.py
odoo/addons/stock_picking_type_user_restriction/readme/CONFIGURE.rst
odoo/addons/stock_picking_type_user_restriction/readme/CONTRIBUTORS.rst
odoo/addons/stock_picking_type_user_restriction/readme/DESCRIPTION.rst
odoo/addons/stock_picking_type_user_restriction/security/ir.model.access.csv
odoo/addons/stock_picking_type_user_restriction/security/stock_security.xml
odoo/addons/stock_picking_type_user_restriction/static/description/icon.png
odoo/addons/stock_picking_type_user_restriction/static/description/index.html
odoo/addons/stock_picking_type_user_restriction/tests/__init__.py
odoo/addons/stock_picking_type_user_restriction/tests/test_picking_type_user_restriction.py
odoo/addons/stock_picking_type_user_restriction/views/product_views.xml
odoo/addons/stock_picking_type_user_restriction/views/stock_inventory_views.xml
odoo/addons/stock_picking_type_user_restriction/views/stock_menu_views.xml
odoo/addons/stock_picking_type_user_restriction/views/stock_picking_type_views.xml
odoo/addons/stock_picking_type_user_restriction/views/stock_picking_views.xml
odoo/addons/stock_picking_type_user_restriction/views/stock_warehouse_views.xml
odoo12_addon_stock_picking_type_user_restriction-12.0.1.0.0.99.dev7.dist-info/METADATA
odoo12_addon_stock_picking_type_user_restriction-12.0.1.0.0.99.dev7.dist-info/WHEEL
odoo12_addon_stock_picking_type_user_restriction-12.0.1.0.0.99.dev7.dist-info/top_level.txt
odoo12_addon_stock_picking_type_user_restriction-12.0.1.0.0.99.dev7.dist-info/RECORD
