Metadata-Version: 2.1
Name: odoo12-addon-stock_picking_type_user_restriction
Version: 12.0.1.0.0.99.dev7
Summary: Restrict some users to see and use only certain picking types
Home-page: https://github.com/OCA/stock-logistics-warehouse
Author: TAKOBI, Odoo Community Association (OCA)
Author-email: support@odoo-community.org
License: LGPL-3
Classifier: Programming Language :: Python
Classifier: Framework :: Odoo
Classifier: Framework :: Odoo :: 12.0
Classifier: License :: OSI Approved :: GNU Lesser General Public License v3 (LGPLv3)
Classifier: Development Status :: 4 - Beta
Requires-Python: >=3.5
Requires-Dist: odoo <12.1dev,>=12.0a
